MANIFEST.in
setup.cfg
setup.py
jdLangTranslator/Icon.png
jdLangTranslator/jdLangTranslator.py
jdLangTranslator.egg-info/PKG-INFO
jdLangTranslator.egg-info/SOURCES.txt
jdLangTranslator.egg-info/dependency_links.txt
jdLangTranslator.egg-info/entry_points.txt
jdLangTranslator.egg-info/requires.txt
jdLangTranslator.egg-info/top_level.txt
jdLangTranslator/translation/de_DE.lang
jdLangTranslator/translation/en_GB.lang