Metadata-Version: 1.1
Name: jdLangTranslator
Version: 1.3
Summary: A Translator for .lang files.
Home-page: https://gitlab.com/JakobDev/jdLangTranslator
Author: JakobDev
Author-email: jakobdev@gmx.de
License: UNKNOWN
Platform: UNKNOWN
Classifier: Typing :: Typed
